submitit_oar/__init__.py
submitit_oar/conftest.py
submitit_oar/oar.py
submitit_oar/test_oar.py
submitit_oar-1.1.1.dist-info/entry_points.txt
submitit_oar-1.1.1.dist-info/LICENSE
submitit_oar-1.1.1.dist-info/WHEEL
submitit_oar-1.1.1.dist-info/METADATA
submitit_oar-1.1.1.dist-info/RECORD
